claude_multi_worker-0.7.1.dist-info/licenses/LICENSE
cmw/__init__.py
cmw/cli.py
cmw/conflict_detector.py
cmw/coordinator.py
cmw/dashboard.py
cmw/dependency_analyzer.py
cmw/dependency_recommender.py
cmw/dependency_validator.py
cmw/error_handler.py
cmw/feedback.py
cmw/git_integration.py
cmw/graph_visualizer.py
cmw/interactive_fixer.py
cmw/migration_orchestrator.py
cmw/models.py
cmw/parallel_executor.py
cmw/progress_tracker.py
cmw/prompt_template.py
cmw/py.typed
cmw/requirements_generator.py
cmw/requirements_parser.py
cmw/response_parser.py
cmw/smart_prompt_generator.py
cmw/state_manager.py
cmw/state_reconciler.py
cmw/static_analyzer.py
cmw/task_filter.py
cmw/task_migrator.py
cmw/task_provider.py
cmw/prompts/requirements_generator.md
claude_multi_worker-0.7.1.dist-info/METADATA
claude_multi_worker-0.7.1.dist-info/WHEEL
claude_multi_worker-0.7.1.dist-info/entry_points.txt
claude_multi_worker-0.7.1.dist-info/top_level.txt
claude_multi_worker-0.7.1.dist-info/RECORD
