Metadata-Version: 2.4
Name: claude-multi-worker
Version: 0.7.1
Summary: ⚠️ DEPRECATED: This package has been renamed to 'clauxton'. Please use: pip install clauxton
Author-email: Nakishiyama <noreply@example.com>
License-Expression: MIT
Project-URL: Homepage, https://github.com/nakishiyaman/cmw
Project-URL: Documentation, https://github.com/nakishiyaman/cmw/wiki
Project-URL: Repository, https://github.com/nakishiyaman/cmw
Project-URL: Issues, https://github.com/nakishiyaman/cmw/issues
Keywords: claude,claude-code,task-management,automation,development,requirements,progress-tracking
Classifier: Development Status :: 3 - Alpha
Classifier: Intended Audience :: Developers
Classifier: Programming Language :: Python :: 3
Classifier: Programming Language :: Python :: 3.9
Classifier: Programming Language :: Python :: 3.10
Classifier: Programming Language :: Python :: 3.11
Classifier: Programming Language :: Python :: 3.12
Requires-Python: >=3.9
License-File: LICENSE
Requires-Dist: click>=8.1.0
Requires-Dist: rich>=13.7.0
Requires-Dist: networkx>=3.0
Provides-Extra: dev
Requires-Dist: pytest>=7.0; extra == "dev"
Requires-Dist: pytest-cov>=4.0; extra == "dev"
Requires-Dist: pytest-asyncio>=0.21; extra == "dev"
Requires-Dist: black>=23.0; extra == "dev"
Requires-Dist: mypy>=1.0; extra == "dev"
Requires-Dist: ruff>=0.1; extra == "dev"
Requires-Dist: types-networkx>=3.0; extra == "dev"
Provides-Extra: dashboard
Requires-Dist: fastapi>=0.100; extra == "dashboard"
Requires-Dist: uvicorn>=0.23; extra == "dashboard"
Requires-Dist: jinja2>=3.1; extra == "dashboard"
Dynamic: license-file
